bert_serving/__init__.py
bert_serving/client/__init__.py
bert_serving/client/_py2_var.py
bert_serving/client/_py3_var.py
bert_serving_multilingual_client-0.0.1.dist-info/DESCRIPTION.rst
bert_serving_multilingual_client-0.0.1.dist-info/METADATA
bert_serving_multilingual_client-0.0.1.dist-info/RECORD
bert_serving_multilingual_client-0.0.1.dist-info/WHEEL
bert_serving_multilingual_client-0.0.1.dist-info/metadata.json
bert_serving_multilingual_client-0.0.1.dist-info/top_level.txt
