Metadata-Version: 2.0
Name: bert-serving-multilingual-client
Version: 0.0.1
Summary: Mapping a variable-length sentence to a fixed-length vector using BERT model (Client)
Home-page: https://github.com/htw5295/bert-as-service
Author: TaeWook Hwang
Author-email: taewook5295@gmail.com
License: MIT
Keywords: bert nlp tensorflow machine learning sentence encoding embedding serving
Platform: UNKNOWN
Classifier: Programming Language :: Python :: 2.7
Classifier: Programming Language :: Python :: 3.6
Classifier: License :: OSI Approved :: MIT License
Classifier: Operating System :: OS Independent
Classifier: Topic :: Scientific/Engineering :: Artificial Intelligence
Requires-Dist: numpy
Requires-Dist: pyzmq (>=17.1.0)
